mathsfunlib/__init__.py
mathsfunlib/qgenerator.py
mathsfunlib-0.0.2.dist-info/METADATA
mathsfunlib-0.0.2.dist-info/WHEEL
mathsfunlib-0.0.2.dist-info/top_level.txt
mathsfunlib-0.0.2.dist-info/RECORD
