Metadata-Version: 2.1
Name: mathsfunlib
Version: 0.0.2
Summary: Maths speed test question generator
Home-page: https://github.com/yogeswarant/mathsfunlib
Author: Yogeswaran Thulasidoss
Author-email: yogeeswaran@gmail.com
License: UNKNOWN
Platform: UNKNOWN
Classifier: Programming Language :: Python :: 3
Classifier: License :: OSI Approved :: MIT License
Classifier: Operating System :: OS Independent
Requires-Python: >=3.6
